ign_las_digital_models-3.0.1.dist-info/licenses/LICENSE
las_digital_models/__init__.py
las_digital_models/dhm_one_tile.py
las_digital_models/ip_one_tile.py
las_digital_models/main.py
las_digital_models/version.py
las_digital_models/commons/__init__.py
las_digital_models/commons/commons.py
las_digital_models/extract_stat_from_raster/extract_z_virtual_lines_from_raster.py
las_digital_models/extract_stat_from_raster/rasters/extract_z_min_from_raster_by_polylines.py
las_digital_models/extract_stat_from_raster/vectors/clip_geometry.py
las_digital_models/tasks/__init__.py
las_digital_models/tasks/dhm_generation.py
las_digital_models/tasks/las_interpolation.py
las_digital_models/tasks/postprocessing.py
test/__init__.py
test/test_dhm_one_tile.py
test/test_ip_one_tile.py
test/test_main.py
test/test_pdal.py
test/test_run_script.py
test/extract_stat_from_raster/test_clip_geometry.py
test/extract_stat_from_raster/test_extract_min_z_from_raster_by_polylines.py
test/extract_stat_from_raster/test_extract_z_virtual_lines_from_raster.py
test/tasks/test_las_interpolation.py
test/utils/__init__.py
test/utils/generate_test_tiles.py
test/utils/point_cloud_utils.py
test/utils/raster_utils.py
ign_las_digital_models-3.0.1.dist-info/METADATA
ign_las_digital_models-3.0.1.dist-info/WHEEL
ign_las_digital_models-3.0.1.dist-info/top_level.txt
ign_las_digital_models-3.0.1.dist-info/RECORD
