Metadata-Version: 2.4
Name: ign-las-digital-models
Version: 3.0.1
Summary: Library to create and perform misc operations on Digital Models generated from LAS files
Author-email: Malvina Dupays <malvina.dupays@ign.fr>, Léa Vauchier <lea.vauchier@ign.fr>
License-File: LICENSE
Dynamic: license-file
